include/permanent/combinatoric.h
include/permanent/common.h
include/permanent/complex.h
include/permanent/glynn.h
include/permanent/kperm-gray.h
include/permanent/opt.h
include/permanent/perm-mv0.h
include/permanent/ryser.h
include/permanent/swap.h
include/permanent/tables.h
include/permanent/tuning.default.h
include/permanent/tuning.h
permanent.cp39-win_amd64.pyd
share/MatrixPermanent/cmake/MatrixPermanentConfig.cmake
share/MatrixPermanent/cmake/MatrixPermanentConfigVersion.cmake
share/MatrixPermanent/cmake/MatrixPermanentTargets.cmake
qc_permanent-0.0.0.dist-info/METADATA
qc_permanent-0.0.0.dist-info/WHEEL
qc_permanent-0.0.0.dist-info/licenses/LICENSE
qc_permanent-0.0.0.dist-info/RECORD
