Metadata-Version: 2.2
Name: qc-permanent
Version: 0.0.0
Summary: Extension module for computing permanents of square and rectangular matrices.
Keywords: math,linear algebra,combinatorics,permanent
Author-Email: QC-Devs <qcdevs@gmail.com>
License:                     GNU GENERAL PUBLIC LICENSE
Classifier: Development Status :: 4 - Beta
Classifier: Environment :: Console
Classifier: License :: OSI Approved :: GNU General Public License v3 or later (GPLv3+)
Classifier: Operating System :: POSIX :: Linux
Classifier: Operating System :: MacOS
Classifier: Operating System :: Microsoft :: Windows
Classifier: Topic :: Scientific/Engineering :: Mathematics
Classifier: Intended Audience :: Science/Research
Classifier: Intended Audience :: Education
Classifier: Intended Audience :: Developers
Classifier: Natural Language :: English
Classifier: Programming Language :: Python :: 3.9
Classifier: Programming Language :: Python :: 3.10
Classifier: Programming Language :: Python :: 3.11
Classifier: Programming Language :: Python :: 3.12
Project-URL: home, https://permanent.qcdevs.org/
Requires-Python: >=3.9
Requires-Dist: numpy>=2.0
Provides-Extra: test
Requires-Dist: pytest; extra == "test"
